tests/test_tsqloader.py
tsqloader/__init__.py
tsqloader/tsqloader.py
tsqloader-0.1.1.dist-info/licenses/LICENSE
tsqloader-0.1.1.dist-info/METADATA
tsqloader-0.1.1.dist-info/WHEEL
tsqloader-0.1.1.dist-info/top_level.txt
tsqloader-0.1.1.dist-info/RECORD
