Metadata-Version: 2.4
Name: tsqloader
Version: 0.1.1
Summary: Db handler wrapper for interacting with a SQL database using SQLAlchemy.
Author: sb5m
License: MIT
Classifier: Programming Language :: Python :: 3
Classifier: Operating System :: OS Independent
Classifier: Topic :: Software Development :: Libraries
Classifier: Topic :: Database
Classifier: License :: OSI Approved :: MIT License
Requires-Python: >=3.8
License-File: LICENSE
Requires-Dist: SQLAlchemy>2.0.0
Dynamic: license-file
